umelogging/__init__.py
umelogging/config.py
umelogging/context.py
umelogging/filters.py
umelogging/formatter.py
umelogging/fastapi/middleware.py
umelogging/otel/handler.py
ume_logging-0.0.16.dist-info/METADATA
ume_logging-0.0.16.dist-info/WHEEL
ume_logging-0.0.16.dist-info/top_level.txt
ume_logging-0.0.16.dist-info/RECORD
