Metadata-Version: 2.4
Name: ume-logging
Version: 0.0.16
Summary: Uniform JSON logging for University Medicine Essen (UME)
Author-email: Felix Nensa <felix.nensa@uk-essen.de>
Project-URL: Homepage, https://pypi.org/project/ume-logging/
Requires-Python: >=3.9
Requires-Dist: python-dateutil>=2.8.2
Requires-Dist: pytz>=2024.1
Provides-Extra: fastapi
Requires-Dist: fastapi>=0.110; extra == "fastapi"
Provides-Extra: otel
Requires-Dist: opentelemetry-api>=1.25.0; extra == "otel"
Requires-Dist: opentelemetry-sdk>=1.25.0; extra == "otel"
Requires-Dist: opentelemetry-exporter-otlp-proto-http>=1.25.0; extra == "otel"
Provides-Extra: dev
Requires-Dist: pytest>=8.0; extra == "dev"
Requires-Dist: pytest-asyncio>=0.23; extra == "dev"
Requires-Dist: httpx>=0.27; extra == "dev"
Requires-Dist: fastapi>=0.110; extra == "dev"
Requires-Dist: opentelemetry-api>=1.25.0; extra == "dev"
Requires-Dist: opentelemetry-sdk>=1.25.0; extra == "dev"
Requires-Dist: opentelemetry-exporter-otlp-proto-http>=1.25.0; extra == "dev"
